LICENSE.txt
MANIFEST.in
README.rst
requirements.txt
setup.cfg
setup.py
model_util/__init__.py
model_util/__init__.pyc
model_util.egg-info/PKG-INFO
model_util.egg-info/SOURCES.txt
model_util.egg-info/dependency_links.txt
model_util.egg-info/requires.txt
model_util.egg-info/top_level.txt
model_util/calculator/__init__.py
model_util/calculator/indicator_caculator/__init__.py
model_util/calculator/indicator_caculator/alpha_calc.py
model_util/calculator/indicator_caculator/annualized_downside_risk_calc.py
model_util/calculator/indicator_caculator/annualized_risk_calc.py
model_util/calculator/indicator_caculator/annualized_ror_calc.py
model_util/calculator/indicator_caculator/base_calculator.py
model_util/calculator/indicator_caculator/beta_calc.py
model_util/calculator/indicator_caculator/extra_return_calc.py
model_util/calculator/indicator_caculator/interval_cov_calc.py
model_util/calculator/indicator_caculator/interval_return_calc.py
model_util/calculator/indicator_caculator/interval_var_calc.py
model_util/calculator/indicator_caculator/ir_calc.py
model_util/calculator/indicator_caculator/maxdown_calc.py
model_util/calculator/indicator_caculator/sharpe_calc.py
model_util/calculator/indicator_caculator/sortino_calc.py
model_util/calculator/indicator_caculator/treynor_calc.py
model_util/calculator/nav_calc/__init__.py
model_util/calculator/nav_calc/portfolio_nav_calc.py
model_util/constant/__init__.py
model_util/constant/constant.py
model_util/constant/horizon.py
model_util/constant/indicator_constant.py
model_util/job/__init__.py
model_util/job/base_job.py
model_util/job/example_job.py
model_util/service/__init__.py
model_util/service/base_service.py
model_util/service/example_service.py
model_util/utils/__init__.py
model_util/utils/base_dao.py
model_util/utils/conf_util.py
model_util/utils/custom_decorator.py
model_util/utils/date_util.py
model_util/utils/dbtemplate.py
model_util/utils/json_util.py
model_util/utils/log_util.py
model_util/utils/mvo_util.py
model_util/utils/param_parser.py
model_util/utils/portfolio_nav_calc_util.py
model_util/utils/log_handlers/__init__.py
model_util/utils/log_handlers/syslog_handler.py